search/__init__.py
search/command_line.py
dj_searcher-1.0.0.dist-info/LICENSE.txt
dj_searcher-1.0.0.dist-info/METADATA
dj_searcher-1.0.0.dist-info/WHEEL
dj_searcher-1.0.0.dist-info/entry_points.txt
dj_searcher-1.0.0.dist-info/top_level.txt
dj_searcher-1.0.0.dist-info/RECORD
