Metadata-Version: 2.1
Name: dj-searcher
Version: 1.0.0
Author-email: dongjin2008 <dkim@icsparis.fr>
License: Copyright (c) 2016 The Python Packaging Authority (PyPA)
Classifier: Development Status :: 3 - Alpha
Classifier: License :: OSI Approved :: MIT License
Classifier: Programming Language :: Python :: 3
Classifier: Programming Language :: Python :: 3.7
Classifier: Programming Language :: Python :: 3.8
Classifier: Programming Language :: Python :: 3.9
Classifier: Programming Language :: Python :: 3.10
Classifier: Programming Language :: Python :: 3.11
Classifier: Programming Language :: Python :: 3 :: Only
Requires-Python: >=3.7
License-File: LICENSE.txt
Requires-Dist: google-search-results
Requires-Dist: requests
Requires-Dist: climage
Requires-Dist: click
Provides-Extra: dev
Requires-Dist: check-manifest ; extra == 'dev'
Provides-Extra: test
Requires-Dist: coverage ; extra == 'test'
